tablinum/__about__.py
tablinum/__init__.py
tablinum/tab_fun_dates.py
tablinum/tab_fun_maths.py
tablinum/tab_fun_useful.py
tablinum/tablinum.py
tablinum-0.2.3.dist-info/METADATA
tablinum-0.2.3.dist-info/WHEEL
tablinum-0.2.3.dist-info/entry_points.txt
tablinum-0.2.3.dist-info/licenses/LICENSE
tablinum-0.2.3.dist-info/RECORD
