Metadata-Version: 2.3
Name: tablinum
Version: 0.2.3
Summary: Tablinum is a Python library to make, manipulate, and neatly print tabular output to the console.
Project-URL: Documentation, https://github.com/unknown/tablinum#readme
Project-URL: Issues, https://github.com/unknown/tablinum/issues
Project-URL: Source, https://github.com/unknown/tablinum
Author-email: Toby Thurston <toby.thurston@gmail.com>
License: MIT
Classifier: Development Status :: 4 - Beta
Classifier: Programming Language :: Python
Classifier: Programming Language :: Python :: 3.8
Classifier: Programming Language :: Python :: 3.9
Classifier: Programming Language :: Python :: 3.10
Classifier: Programming Language :: Python :: 3.11
Classifier: Programming Language :: Python :: 3.12
Classifier: Programming Language :: Python :: Implementation :: CPython
Classifier: Programming Language :: Python :: Implementation :: PyPy
Requires-Python: >=3.8
